sphynxml/Assurance_db/__init__.py
sphynxml/Assurance_db/assurance_db_connection.py
sphynxml/BaseModeler.py
sphynxml/Cronjobs/SphynxCron.py
sphynxml/Cronjobs/__init__.py
sphynxml/Cronjobs/example_script.sh
sphynxml/Cronjobs/output_testfile.txt
sphynxml/Cronjobs/test_script.sh
sphynxml/ETL/SphynxETL.py
sphynxml/ETL/__init__.py
sphynxml/Elasticsearch/SphynxElastic.py
sphynxml/Elasticsearch/__init__.py
sphynxml/Elasticsearch/sphynx_elastic_credentials.json
sphynxml/Elasticsearch/tests/SphynxElastic_tests.py
sphynxml/Predictors/SphynxPredictor.py
sphynxml/Predictors/__init__.py
sphynxml/Preprocessors/SphynxEncoder.py
sphynxml/Preprocessors/SphynxFilterer.py
sphynxml/Preprocessors/SphynxTransformer.py
sphynxml/Preprocessors/__init__.py
sphynxml/Preprocessors/tests/preprocessor_tests.py
sphynxml/RabbitMQ/__init__.py
sphynxml/RabbitMQ/listener.py
sphynxml/Statistics/SphynxStatistics.py
sphynxml/Statistics/Statistics.py
sphynxml/Statistics/__init__.py
sphynxml/Validators/BaseValidator.py
sphynxml/Validators/ChiSquaredValidator.py
sphynxml/Validators/KSValidator.py
sphynxml/Validators/MixedTypeTabularValidator.py
sphynxml/Validators/SphynxValidator.py
sphynxml/Validators/__init__.py
sphynxml/__init__.py
sphynxml/tests/__init__.py
sphynxml/tests/conftest.py
sphynxml/tests/pytest.ini
sphynxml/tests/test_Elasticsearch/__init__.py
sphynxml/tests/test_Elasticsearch/test_SphynxElastic.py
sphynxml/tests/test_SphynxETL/__init__.py
sphynxml/tests/test_SphynxETL/test_etl.py
sphynxml/tests/test_preprocessors/__init__.py
sphynxml/tests/test_preprocessors/test_encoder.py
sphynxml/tests/test_preprocessors/test_filterer.py
sphynxml/tests/test_preprocessors/test_transformer.py
sphynxml/tests/test_statistics/__init__.py
sphynxml/tests/test_statistics/test_InferentialStatistics.py
sphynxml/tests/test_statistics/test_InfoStats.py
sphynxml/tests/test_statistics/test_SphynxStatistics.py
sphynxml/tests/test_statistics/test_SummaryStatistics.py
sphynxml/tests/test_utils/__init__.py
sphynxml-2.0.0.dist-info/WHEEL
sphynxml-2.0.0.dist-info/METADATA
sphynxml-2.0.0.dist-info/RECORD
