Metadata-Version: 2.1
Name: sphynxml
Version: 2.0.0
Summary: 
Author: IORDANIS XANTHOPOULOS
Author-email: i.xanthopoulos@sphynx.ch
Requires-Python: >=3.7.1,<3.8.0
Classifier: Programming Language :: Python :: 3
Requires-Dist: Cython (==0.29.26)
Requires-Dist: Django (==3.2.11)
Requires-Dist: Flask (==2.0.2)
Requires-Dist: GitPython (==3.1.26)
Requires-Dist: HeapDict (==1.0.1)
Requires-Dist: Jinja2 (==3.0.3)
Requires-Dist: Mako (==1.1.6)
Requires-Dist: MarkupSafe (==2.0.1)
Requires-Dist: Pillow (==9.0.0)
Requires-Dist: PyWavelets (==1.2.0)
Requires-Dist: PyYAML (==6.0)
Requires-Dist: Pygments (==2.11.2)
Requires-Dist: SQLAlchemy (==1.4.31)
Requires-Dist: Send2Trash (==1.8.0)
Requires-Dist: Sphinx (>=4.3.0,<4.4.0)
Requires-Dist: Werkzeug (==2.0.2)
Requires-Dist: alembic (==1.7.5)
Requires-Dist: argon2-cffi (==21.3.0)
Requires-Dist: argon2-cffi-bindings (==21.2.0)
Requires-Dist: asgiref (==3.5.0)
Requires-Dist: attrs (==21.4.0)
Requires-Dist: backcall (==0.2.0)
Requires-Dist: black (>=22.1.0,<22.2.0)
Requires-Dist: bleach (==4.1.0)
Requires-Dist: catboost (==1.0.4)
Requires-Dist: category-encoders (==2.3.0)
Requires-Dist: celery (>=5.2.3,<6.0.0)
Requires-Dist: certifi (==2021.10.8)
Requires-Dist: cffi (==1.15.0)
Requires-Dist: charset-normalizer (==2.0.10)
Requires-Dist: click (==8.0.3)
Requires-Dist: cloudpickle (==2.0.0)
Requires-Dist: colorama (==0.4.4)
Requires-Dist: coreapi (==2.3.3)
Requires-Dist: coreschema (==0.0.4)
Requires-Dist: coverage (==6.3.1)
Requires-Dist: crontab (>=0.23.0,<0.24.0)
Requires-Dist: cycler (==0.11.0)
Requires-Dist: dask (==2022.1.0)
Requires-Dist: databricks-cli (==0.16.2)
Requires-Dist: debugpy (==1.5.1)
Requires-Dist: decorator (==4.4.2)
Requires-Dist: defusedxml (==0.7.1)
Requires-Dist: distributed (==2022.1.0)
Requires-Dist: djangorestframework (==3.13.1)
Requires-Dist: docker (==5.0.3)
Requires-Dist: drf-yasg (==1.20.0)
Requires-Dist: elasticsearch (==7.17.0)
Requires-Dist: entrypoints (==0.3)
Requires-Dist: evalml (==0.43.0)
Requires-Dist: featuretools (==1.4.0)
Requires-Dist: fonttools (==4.29.0)
Requires-Dist: fsspec (==2022.1.0)
Requires-Dist: gitdb (==4.0.9)
Requires-Dist: graphviz (==0.19.1)
Requires-Dist: greenlet (==1.1.2)
Requires-Dist: gunicorn (==20.1.0)
Requires-Dist: idna (==3.3)
Requires-Dist: imageio (==2.14.1)
Requires-Dist: imbalanced-learn (==0.9.0)
Requires-Dist: importlib-metadata (>=4.2.0,<4.3.0)
Requires-Dist: importlib-resources (==5.4.0)
Requires-Dist: inflection (==0.5.1)
Requires-Dist: iniconfig (==1.1.1)
Requires-Dist: ipykernel (==6.7.0)
Requires-Dist: ipython (==7.31.1)
Requires-Dist: ipython_genutils (==0.2.0)
Requires-Dist: ipywidgets (==7.6.5)
Requires-Dist: itsdangerous (==2.0.1)
Requires-Dist: itypes (==1.2.0)
Requires-Dist: jedi (==0.18.1)
Requires-Dist: joblib (==1.1.0)
Requires-Dist: jsonschema (==4.4.0)
Requires-Dist: jupyter-client (==7.1.2)
Requires-Dist: jupyter-core (==4.9.1)
Requires-Dist: jupyterlab-pygments (==0.1.2)
Requires-Dist: jupyterlab-widgets (==1.0.2)
Requires-Dist: kaleido (==0.2.1)
Requires-Dist: kiwisolver (==1.3.2)
Requires-Dist: lightgbm (==3.3.2)
Requires-Dist: lime (==0.2.0.1)
Requires-Dist: llvmlite (==0.38.0)
Requires-Dist: locket (==0.2.1)
Requires-Dist: matplotlib (==3.5.1)
Requires-Dist: matplotlib-inline (==0.1.3)
Requires-Dist: mistune (==0.8.4)
Requires-Dist: mlflow (==1.23.0)
Requires-Dist: model-bakery (==1.4.0)
Requires-Dist: msgpack (==1.0.3)
Requires-Dist: mypy-extensions (==0.4.3)
Requires-Dist: nbclient (==0.5.10)
Requires-Dist: nbconvert (==6.4.0)
Requires-Dist: nbformat (==5.1.3)
Requires-Dist: nest-asyncio (==1.5.4)
Requires-Dist: networkx (==2.5.1)
Requires-Dist: nlp-primitives (==2.1.0)
Requires-Dist: nltk (==3.6.5)
Requires-Dist: notebook (==6.4.8)
Requires-Dist: numba (==0.55.0)
Requires-Dist: numpy (==1.21.5)
Requires-Dist: packaging (==21.3)
Requires-Dist: pandas (==1.3.5)
Requires-Dist: pandocfilters (==1.5.0)
Requires-Dist: parso (==0.8.3)
Requires-Dist: partd (==1.2.0)
Requires-Dist: pathspec (==0.9.0)
Requires-Dist: patsy (==0.5.2)
Requires-Dist: pexpect (==4.8.0)
Requires-Dist: pickleshare (==0.7.5)
Requires-Dist: pika (>=1.2.0,<2.0.0)
Requires-Dist: platformdirs (==2.4.1)
Requires-Dist: plotly (==5.5.0)
Requires-Dist: pluggy (==1.0.0)
Requires-Dist: pmdarima (==1.8.4)
Requires-Dist: prometheus-client (==0.13.0)
Requires-Dist: prometheus-flask-exporter (==0.18.7)
Requires-Dist: prompt-toolkit (==3.0.24)
Requires-Dist: protobuf (==3.19.3)
Requires-Dist: psutil (==5.9.0)
Requires-Dist: psycopg2 (==2.9.3)
Requires-Dist: ptyprocess (==0.7.0)
Requires-Dist: py (==1.11.0)
Requires-Dist: pyaml (==21.10.1)
Requires-Dist: pycparser (==2.21)
Requires-Dist: pyparsing (==3.0.7)
Requires-Dist: pyrsistent (==0.18.1)
Requires-Dist: pytest (==6.2.5)
Requires-Dist: pytest-cov (>=3.0.0,<4.0.0)
Requires-Dist: pytest-django (==4.5.2)
Requires-Dist: python-dateutil (==2.8.2)
Requires-Dist: pytz (==2021.3)
Requires-Dist: pyzmq (==22.3.0)
Requires-Dist: querystring-parser (==1.2.4)
Requires-Dist: regex (==2022.1.18)
Requires-Dist: requests (==2.27.1)
Requires-Dist: requirements-parser (==0.5.0)
Requires-Dist: ruamel.yaml (==0.17.20)
Requires-Dist: ruamel.yaml.clib (==0.2.6)
Requires-Dist: scikit-image (==0.19.1)
Requires-Dist: scikit-learn (==1.0.2)
Requires-Dist: scikit-optimize (==0.9.0)
Requires-Dist: scipy (==1.7.3)
Requires-Dist: seaborn (==0.11.2)
Requires-Dist: shap (==0.40.0)
Requires-Dist: six (==1.16.0)
Requires-Dist: sktime (==0.8.0)
Requires-Dist: slicer (==0.0.7)
Requires-Dist: smmap (==5.0.0)
Requires-Dist: sortedcontainers (==2.4.0)
Requires-Dist: sqlparse (==0.4.2)
Requires-Dist: statsmodels (==0.13.1)
Requires-Dist: tabulate (==0.8.9)
Requires-Dist: tblib (==1.7.0)
Requires-Dist: tenacity (==8.0.1)
Requires-Dist: terminado (==0.12.1)
Requires-Dist: testpath (==0.5.0)
Requires-Dist: texttable (==1.6.4)
Requires-Dist: threadpoolctl (==3.0.0)
Requires-Dist: tifffile (==2021.11.2)
Requires-Dist: toml (==0.10.2)
Requires-Dist: tomli (==1.2.3)
Requires-Dist: toolz (==0.11.2)
Requires-Dist: tornado (==6.1)
Requires-Dist: tqdm (==4.62.3)
Requires-Dist: traitlets (==5.1.1)
Requires-Dist: typed-ast (==1.5.2)
Requires-Dist: types-setuptools (==57.4.7)
Requires-Dist: typing-extensions (==4.0.1)
Requires-Dist: uritemplate (==4.1.1)
Requires-Dist: urllib3 (==1.26.8)
Requires-Dist: vowpalwabbit (==8.11.0)
Requires-Dist: wcwidth (==0.2.5)
Requires-Dist: webencodings (==0.5.1)
Requires-Dist: websocket-client (==1.2.3)
Requires-Dist: widgetsnbextension (==3.5.2)
Requires-Dist: woodwork (==0.11.1)
Requires-Dist: xgboost (==1.5.2)
Requires-Dist: zict (==2.0.0)
Requires-Dist: zipp (==3.7.0)
